JupyterDebug/__init__.py
JupyterDebug/core.py
JupyterDebug/utils.py
JupyterDebug-0.1.0.dist-info/LICENSE
JupyterDebug-0.1.0.dist-info/METADATA
JupyterDebug-0.1.0.dist-info/WHEEL
JupyterDebug-0.1.0.dist-info/top_level.txt
JupyterDebug-0.1.0.dist-info/RECORD
