Metadata-Version: 2.1
Name: JupyterDebug
Version: 0.1.0
Summary: A package for debugging Jupyter notebooks using OpenAI.
Home-page: https://github.com/et22/JupyterDebug
Author: Ethan
Author-email: your.email@example.com
Classifier: Programming Language :: Python :: 3
Classifier: License :: OSI Approved :: MIT License
Classifier: Operating System :: OS Independent
Requires-Python: >=3.6
License-File: LICENSE
Requires-Dist: openai (>=1.9.0)
Requires-Dist: ipython (>=7.34.0)
Requires-Dist: ipywidgets (>=7.7.1)
Provides-Extra: dev
Requires-Dist: black (>=22.0.0) ; extra == 'dev'
Requires-Dist: flake8 (>=4.0.0) ; extra == 'dev'
Provides-Extra: test
Requires-Dist: pytest (>=6.0.0) ; extra == 'test'
